Katari/__init__.py
Katari/client/__init__.py
Katari/errors/__init__.py
Katari/interfaces/__init__.py
Katari/logging/__init__.py
Katari/managment/__init__.py
Katari/managment/commands/__init__.py
Katari/managment/commands/build_app.py
Katari/managment/commands/client.py
Katari/managment/utils/__init__.py
Katari/middleware/__init__.py
Katari/middleware/sessions.py
Katari/models/__init__.py
Katari/server/__init__.py
Katari/server/tcp/__init__.py
Katari/server/udp/__init__.py
Katari/sip/__init__.py
Katari/sip/response/_1xx.py
Katari/sip/response/_2xx.py
Katari/sip/response/_3xx.py
Katari/sip/response/_4xx.py
Katari/sip/response/__init__.py
Katari/sip/utils/__init__.py
Katari/template/__init__.py
Katari/template/app.py
Katari/template/settings.py
Katari-0.0.9.data/scripts/katari
scripts/__init__.py
Katari-0.0.9.dist-info/LICENSE
Katari-0.0.9.dist-info/METADATA
Katari-0.0.9.dist-info/WHEEL
Katari-0.0.9.dist-info/top_level.txt
Katari-0.0.9.dist-info/RECORD
