Metadata-Version: 2.1
Name: Katari
Version: 0.0.9
Summary: A SIP(Session Initiation Protocol) Application Framework
Home-page: http://packages.python.org/Katari
Author: Aaron Parfitt
Author-email: aaronparfitt123@gmail.com
License: BSD
Keywords: voip
Platform: UNKNOWN
Classifier: Development Status :: 5 - Production/Stable
Classifier: Programming Language :: Python :: 3.6
Classifier: Topic :: Software Development :: Libraries :: Application Frameworks
